{
"companyName": "DefaultCompany",
"productName": "Impossible track race",
"productVersion": "1.0",
"dataUrl": "Impossible Moto Race.data.unityweb",
"wasmCodeUrl": "Impossible Moto Race.wasm.code.unityweb",
"wasmFrameworkUrl": "Impossible Moto Race.wasm.framework.unityweb",
"graphicsAPI": ["WebGL 2.0","WebGL 1.0"],
"webglContextAttributes": {"preserveDrawingBuffer": false},
"splashScreenStyle": "Dark",
"backgroundColor": "#231F20",
"developmentBuild": false,
"multithreading": false,
"unityVersion": "2019.4.34f1"
}